{"paths":{},"types":[],"uuids":["12CZPBIuFJpo6qmGnizYrg","2dL3kvpAxJu6GJ7RdqJG5J","6aoKpq6+5BVaCIpoemqt7E","a8Anh32NZGRZegUtSgEj26","afwVKIphdIOKmDdJXQGMXg","b2sUAiF59Ff7K8yhqF7Jbf","19jh2mVbhKPpFGGAezc3Qj","29FYIk+N1GYaeWH/q1NxQO","31vIlawANFZqnzLlSuHBfc","41D7kWhyFGY7q4NDlzkazn","675ovJ2tVK2aLYfgPUWOMv","7a/QZLET9IDreTiBfRn2PD","8855/VlrRKd6H0MSRnFxAU","9bvaMerUlDyary99mJa6xp","a2MjXRFdtLlYQ5ouAFv/+R","e97GVMl6JHh5Ml5qEDdSGa","ecpdLyjvZBwrvm+cedCcQy","f0BIwQ8D5Ml7nTNQbh1YlS"],"scenes":{"db://assets/Scene/game.fire":4,"db://assets/Scene/helloworld.fire":1,"db://assets/Scene/loading.fire":5,"db://assets/Scene/main.fire":0},"redirect":[6,0,7,0,10,0,11,1,12,0,13,0,14,0,15,0,16,1,17,0],"deps":["resources","internal"],"packs":{"05dd1dc0e":[1,8,9],"0cfd22b7a":[2,3]},"name":"main","importBase":"import","nativeBase":"native","debug":false,"isZip":false,"encrypted":false,"versions":{"import":["05dd1dc0e","31ab4","0cfd22b7a","b2b05",0,"2130f",4,"7a828",5,"8e586"],"native":[2,"55ea4",3,"cea68"]}}