{"paths":{},"types":[],"uuids":["03EyEfMaNCeYz6IS4nsO5N","12CZPBIuFJpo6qmGnizYrg","29FYIk+N1GYaeWH/q1NxQO","2dL3kvpAxJu6GJ7RdqJG5J","6aoKpq6+5BVaCIpoemqt7E","71VhFCTINJM6/Ky3oX9nBT","99FwsL0hBG8bITfZ4/IwmK","a8Anh32NZGRZegUtSgEj26","b2sUAiF59Ff7K8yhqF7Jbf","b4P/PCArtIdIH38t6mlw8Y","cf73jxyN9Jt47QTJU6ziYh","d8HsitJHxOYqo801xBk8ev","e8Ueib+qJEhL6mXAHdnwbi","e97GVMl6JHh5Ml5qEDdSGa","f0BIwQ8D5Ml7nTNQbh1YlS","31vIlawANFZqnzLlSuHBfc","41D7kWhyFGY7q4NDlzkazn","675ovJ2tVK2aLYfgPUWOMv","8855/VlrRKd6H0MSRnFxAU","9bvaMerUlDyary99mJa6xp","a2MjXRFdtLlYQ5ouAFv/+R","ecpdLyjvZBwrvm+cedCcQy","edJ1HgEB5G5qMmDq56zi3A"],"scenes":{"db://assets/Scene/game.fire":0,"db://assets/Scene/helloworld.fire":3,"db://assets/Scene/loading.fire":8,"db://assets/Scene/main.fire":1},"redirect":[20,0,21,1,22,0],"deps":["resources","internal"],"packs":{"048a38ca6":[0,2,17,18,13,14],"05dd1dc0e":[3,15,16],"0795cca7f":[1,2,19,13,14],"08ccb46f1":[4,5,6,7,9,10,11,12]},"name":"main","importBase":"import","nativeBase":"native","debug":false,"isZip":false,"encrypted":false,"versions":{"import":["048a38ca6","4ac16","05dd1dc0e","31ab4","0795cca7f","daf18","08ccb46f1","fc990",8,"dd63c"],"native":[4,"55ea4",5,"c06a9",6,"d1118",7,"cea68",9,"83fcc",10,"a4b59",11,"cdbc9",12,"90cf4"]}}